{
  "stock": [
    {
      "Symbol": "AAPL",
      "Close": [150, 153, 155, 148],
      "Open": [149, 152, 157, 147],
      "High": [156, 154, 158, 151],
      "Low": [147, 150, 151, 146],
      "Volume": [1000000, 2000000, 3000000, 4000000]
    },
    {
      "Symbol": "MSFT",
      "Close": [210, 212, 215, 209],
      "Open": [211, 213, 216, 208],
      "High": [215, 214, 217, 211],
      "Low": [208, 211, 212, 207],
      "Volume": [1000000, 2000000, 3000000, 4000000]
    },
    {
        "Symbol": "GOOGL",
      "Close": [2720, 2730, 2745, 2715],
      "Open": [2718, 2725, 2750, 2700],
      "High": [2740, 2735, 2760, 2720],
      "Low": [2705, 2720, 2725, 2695],
      "Volume": [1000000, 2000000, 3000000, 4000000]
    },
    {
        "Symbol": "AMZN",
      "Close": [3300, 3320, 3340, 3280],
      "Open": [3290, 3310, 3350, 3270],
      "High": [3350, 3330, 3360, 3295],
      "Low": [3275, 3300, 3310, 3265],
      "Volume": [1000000, 2000000, 3000000, 4000000]
    },
    {
      "Symbol": "TSLA",
      "Close": [680, 685, 690, 675],
      "Open": [678, 682, 695, 670],
      "High": [690, 687, 700, 680],
      "Low": [670, 680, 682, 665],
      "Volume": [1000000, 2000000, 3000000, 4000000]
    }
  ],
  "symbols": ["AAPL", "MSFT", "GOOGL", "AMZN", "TSLA"],
  "price": {
    "returns": {
      "AAPL": [0.01, 0.02, 0.03, 0.04],
      "MSFT": [0.01, 0.02, 0.03, 0.04],
      "GOOGL": [0.01, 0.02, 0.03, 0.04],
      "AMZN": [0.01, 0.02, 0.03, 0.04],
      "TSLA": [0.01, 0.02, 0.03, 0.04]
    },
    "log_returns": {
      "AAPL": [0.01, 0.02, 0.03, 0.04],
      "MSFT": [0.01, 0.02, 0.03, 0.04],
      "GOOGL": [0.01, 0.02, 0.03, 0.04],
      "AMZN": [0.01, 0.02, 0.03, 0.04],
      "TSLA": [0.01, 0.02, 0.03, 0.04]
    },
    "autocorrelation": {
      "AAPL": [0.02, 0.03, 0.04],
      "MSFT": [0.02, 0.03, 0.04],
      "GOOGL": [0.02, 0.03, 0.04],
      "AMZN": [0.02, 0.03, 0.04],
      "TSLA": [0.02, 0.03, 0.04]
    }
  },
  "volatility": {
    "returns": {
      "AAPL": [0.01, 0.02, 0.03, 0.04],
      "MSFT": [0.01, 0.02, 0.03, 0.04],
      "GOOGL": [0.01, 0.02, 0.03, 0.04],
      "AMZN": [0.01, 0.02, 0.03, 0.04],
      "TSLA": [0.01, 0.02, 0.03, 0.04]
    },
    "log_returns": {
      "AAPL": [0.01, 0.02, 0.03, 0.04],
      "MSFT": [0.01, 0.02, 0.03, 0.04],
      "GOOGL": [0.01, 0.02, 0.03, 0.04],
      "AMZN": [0.01, 0.02, 0.03, 0.04],
      "TSLA": [0.01, 0.02, 0.03, 0.04]
    },
    "autocorrelation": {
      "AAPL": [0.02, 0.03, 0.04],
      "MSFT": [0.02, 0.03, 0.04],
      "GOOGL": [0.02, 0.03, 0.04],
      "AMZN": [0.02, 0.03, 0.04],
      "TSLA": [0.02, 0.03, 0.04]
    }
  },
  "moving_average": {
    "returns": {
      "AAPL": [0.01, 0.02, 0.03, 0.04],
      "MSFT": [0.01, 0.02, 0.03, 0.04],
      "GOOGL": [0.01, 0.02, 0.03, 0.04],
      "AMZN": [0.01, 0.02, 0.03, 0.04],
      "TSLA": [0.01, 0.02, 0.03, 0.04]
    },
    "log_returns": {
      "AAPL": [0.01, 0.02, 0.03, 0.04],
      "MSFT": [0.01, 0.02, 0.03, 0.04],
      "GOOGL": [0.01, 0.02, 0.03, 0.04],
      "AMZN": [0.01, 0.02, 0.03, 0.04],
      "TSLA": [0.01, 0.02, 0.03, 0.04]
    },
    "autocorrelation": {
      "AAPL": [0.02, 0.03, 0.04],
      "MSFT": [0.02, 0.03, 0.04],
      "GOOGL": [0.02, 0.03, 0.04],
      "AMZN": [0.02, 0.03, 0.04],
      "TSLA": [0.02, 0.03, 0.04]
    }
  }
}
